{"window.screen":{"mozLockOrientation":{ toString : function () { return "function mozLockOrientation() {    [native code]}";}},"mozUnlockOrientation":{ toString : function () { return "function mozUnlockOrientation() {    [native code]}";}},"availWidth":1366,"availHeight":728,"width":1366,"height":768,"colorDepth":24,"pixelDepth":24,"top":0,"left":0,"availTop":0,"availLeft":0,"mozOrientation":"landscape-primary","onmozorientationchange":null,"orientation":{"lock":[""],"unlock":[""],"type":"landscape-primary","angle":0,"onchange":null,"addEventListener":[""],"removeEventListener":[""],"dispatchEvent":[""],toString: function () {return "[object ScreenOrientation]";}},"addEventListener":{ toString : function () { return "function addEventListener() {    [native code]}";}},"removeEventListener":{ toString : function () { return "function removeEventListener() {    [native code]}";}},"dispatchEvent":{ toString : function () { return "function dispatchEvent() {    [native code]}";}}},"window":{"navigator":{"getBattery":{ toString : function () { return "function getBattery() {    [native code]}";}},"vibrate":{ toString : function () { return "function vibrate() {    [native code]}";}},"javaEnabled":function javaEnabled() {return true;},"getGamepads":{ toString : function () { return "function getGamepads() {    [native code]}";}},"mozGetUserMedia":{ toString : function () { return "function mozGetUserMedia() {    [native code]}";}},"sendBeacon":{ toString : function () { return "function sendBeacon() {    [native code]}";}},"requestMediaKeySystemAccess":{ toString : function () { return "function requestMediaKeySystemAccess() {    [native code]}";}},"registerProtocolHandler":{ toString : function () { return "function registerProtocolHandler() {    [native code]}";}},"registerContentHandler":{ toString : function () { return "function registerContentHandler() {    [native code]}";}},"taintEnabled":{ toString : function () { return "function taintEnabled() {    [native code]}";}},"permissions":{"query":[""],"revoke":[""],toString: function () {return "[object Permissions]";}},"mimeTypes":{ toString : function () {       return "[object MimeTypeArray]";}},"plugins":{ toString : function () {       return "[object PluginArray]";}},"doNotTrack":"unspecified","battery":{"charging":true,"chargingTime":0,"dischargingTime":null,"level":1,"onchargingchange":null,"onchargingtimechange":null,"ondischargingtimechange":null,"onlevelchange":null,"addEventListener":[""],"removeEventListener":[""],"dispatchEvent":[""],toString: function () {return "[object BatteryManager]";}},"oscpu":"Windows NT 6.1; WOW64","vendor":"","vendorSub":"","productSub":"20100101","cookieEnabled":true,"buildID":"20160922113459","mediaDevices":{"getSupportedConstraints":[""],"enumerateDevices":[""],"getUserMedia":[""],"addEventListener":[""],"removeEventListener":[""],"dispatchEvent":[""],toString: function () {return "[object MediaDevices]";}},"serviceWorker":{"controller":null,"register":[""],"getRegistration":[""],"getRegistrations":[""],"ready":{},"oncontrollerchange":null,"onerror":null,"onmessage":null,"addEventListener":[""],"removeEventListener":[""],"dispatchEvent":[""],toString: function () {return "[object ServiceWorkerContainer]";}},"hardwareConcurrency":2,"geolocation":{"getCurrentPosition":[""],"watchPosition":[""],"clearWatch":[""],toString: function () {return "[object Geolocation]";}},"appCodeName":"Mozilla","appName":"Netscape","appVersion":"5.0 (Windows)","platform":"Win32","userAgent":"Mozilla/5.0 (Windows NT 6.1; WOW64; rv:49.0) Gecko/20100101 Firefox/49.0","product":"Gecko","language":"ru-RU","languages":{"0":"ru-RU","1":"ru","2":"en-US","3":"en",toString: function () {return "ru-RU,ru,en-US,en";}},"onLine":true},"speechSynthesis":{toString: function () {       return "[object speechSynthesis]";}},"RTCPeerConnection":{toString: function () {return "function RTCPeerConnection() { [native code] }";}},"RTCSessionDescription":{toString: function () {return "function RTCSessionDescription() { [native code] }";}},"MediaStreamTrack":{toString: function () {return "function MediaStreamTrack() { [native code] }";}},"indexedDB":{toString: function () {       return "[object indexedDB]";}},"devicePixelRatio":1,"outerWidth":1382,"innerWidth":1366,"innerHeight":657},"window.navigator.plugins":{"0":{"0":{"description":"nptswp.dll","enabledPlugin":[{}],"suffixes":"","type":"application/x-nptswp"},"application/x-nptswp":{"description":"nptswp.dll","enabledPlugin":[{}],"suffixes":"","type":"application/x-nptswp"},"item":[""],"namedItem":[""],"description":"360 Total Security","filename":"nptswp.dll","version":"6.0.0.1004","name":"360 Total Security","length":1,toString: function () {return "[object Plugin]";}},"1":{"0":{"description":"Acrobat Portable Document Format","enabledPlugin":[{}],"suffixes":"pdf","type":"application/pdf"},"1":{"description":"Adobe PDF in XML Format","enabledPlugin":[{}],"suffixes":"pdfxml","type":"application/vnd.adobe.pdfxml"},"2":{"description":"Adobe PDF in XML Format","enabledPlugin":[{}],"suffixes":"mars","type":"application/vnd.adobe.x-mars"},"3":{"description":"Acrobat Forms Data Format","enabledPlugin":[{}],"suffixes":"fdf","type":"application/vnd.fdf"},"4":{"description":"XML Version of Acrobat Forms Data Format","enabledPlugin":[{}],"suffixes":"xfdf","type":"application/vnd.adobe.xfdf"},"5":{"description":" Acrobat XML Data Package","enabledPlugin":[{}],"suffixes":"xdp","type":"application/vnd.adobe.xdp+xml"},"6":{"description":"Adobe FormFlow99 Data File","enabledPlugin":[{}],"suffixes":"xfd","type":"application/vnd.adobe.xfd+xml"},"application/pdf":{"description":"Acrobat Portable Document Format","enabledPlugin":[{}],"suffixes":"pdf","type":"application/pdf"},"application/vnd.adobe.pdfxml":{"description":"Adobe PDF in XML Format","enabledPlugin":[{}],"suffixes":"pdfxml","type":"application/vnd.adobe.pdfxml"},"application/vnd.adobe.x-mars":{"description":"Adobe PDF in XML Format","enabledPlugin":[{}],"suffixes":"mars","type":"application/vnd.adobe.x-mars"},"application/vnd.fdf":{"description":"Acrobat Forms Data Format","enabledPlugin":[{}],"suffixes":"fdf","type":"application/vnd.fdf"},"application/vnd.adobe.xfdf":{"description":"XML Version of Acrobat Forms Data Format","enabledPlugin":[{}],"suffixes":"xfdf","type":"application/vnd.adobe.xfdf"},"application/vnd.adobe.xdp+xml":{"description":" Acrobat XML Data Package","enabledPlugin":[{}],"suffixes":"xdp","type":"application/vnd.adobe.xdp+xml"},"application/vnd.adobe.xfd+xml":{"description":"Adobe FormFlow99 Data File","enabledPlugin":[{}],"suffixes":"xfd","type":"application/vnd.adobe.xfd+xml"},"item":[""],"namedItem":[""],"description":"Adobe PDF Plug-In For Firefox and Netscape 15.20.20039","filename":"nppdf32.dll","version":"15.20.20039.7108","name":"Adobe Acrobat","length":7,toString: function () {return "[object Plugin]";}},"2":{"0":{"description":"Authorware","enabledPlugin":[{}],"suffixes":"aam","type":"application/x-authorware-map"},"application/x-authorware-map":{"description":"Authorware","enabledPlugin":[{}],"suffixes":"aam","type":"application/x-authorware-map"},"item":[""],"namedItem":[""],"description":"Macromedia Authorware Web Player Netscape plug-in, version 2004 ","filename":"np32asw.dll","version":"2004.0.0.1","name":"Authorware Web Player","length":1,toString: function () {return "[object Plugin]";}},"3":{"0":{"description":"npmigfpi.dll","enabledPlugin":[{}],"suffixes":"","type":"application/x-eppex-plugin-1"},"application/x-eppex-plugin-1":{"description":"npmigfpi.dll","enabledPlugin":[{}],"suffixes":"","type":"application/x-eppex-plugin-1"},"item":[""],"namedItem":[""],"description":"CANON iMAGE GATEWAY Album Plugin Utility Module for IJ","filename":"npmigfpi.dll","version":"5.0.0.0","name":"CANON iMAGE GATEWAY Album Plugin Utility for IJ","length":1,toString: function () {return "[object Plugin]";}},"4":{"0":{"description":"","enabledPlugin":[{}],"suffixes":"","type":"application/x-vnd.google.update3webcontrol.3"},"1":{"description":"","enabledPlugin":[{}],"suffixes":"","type":"application/x-vnd.google.oneclickctrl.9"},"application/x-vnd.google.update3webcontrol.3":{"description":"","enabledPlugin":[{}],"suffixes":"","type":"application/x-vnd.google.update3webcontrol.3"},"application/x-vnd.google.oneclickctrl.9":{"description":"","enabledPlugin":[{}],"suffixes":"","type":"application/x-vnd.google.oneclickctrl.9"},"item":[""],"namedItem":[""],"description":"Google Update","filename":"npGoogleUpdate3.dll","version":"1.3.31.5","name":"Google Update","length":2,toString: function () {return "[object Plugin]";}},"5":{"0":{"description":"14.0.4730.1010","enabledPlugin":[{}],"suffixes":"*","type":"application/x-msoffice14"},"application/x-msoffice14":{"description":"14.0.4730.1010","enabledPlugin":[{}],"suffixes":"*","type":"application/x-msoffice14"},"item":[""],"namedItem":[""],"description":"Office Authorization plug-in for NPAPI browsers","filename":"NPAUTHZ.DLL","version":"14.0.4730.1010","name":"Microsoft Office 2010","length":1,toString: function () {return "[object Plugin]";}},"6":{"0":{"description":"SharePoint Plug-in for Firefox","enabledPlugin":[{}],"suffixes":"","type":"application/x-sharepoint"},"application/x-sharepoint":{"description":"SharePoint Plug-in for Firefox","enabledPlugin":[{}],"suffixes":"","type":"application/x-sharepoint"},"item":[""],"namedItem":[""],"description":"The plug-in allows you to open and edit files using Microsoft Office applications","filename":"NPSPWRAP.DLL","version":"14.0.4761.1000","name":"Microsoft Office 2010","length":1,toString: function () {return "[object Plugin]";}},"7":{"0":{"description":"npnv3dvstreaming","enabledPlugin":[{}],"suffixes":"rts","type":"application/mozilla-3dv-streaming-plugin"},"application/mozilla-3dv-streaming-plugin":{"description":"npnv3dvstreaming","enabledPlugin":[{}],"suffixes":"rts","type":"application/mozilla-3dv-streaming-plugin"},"item":[""],"namedItem":[""],"description":"NVIDIA 3D Vision Streaming plugin for Mozilla browsers","filename":"npnv3dvstreaming.dll","version":"7.17.12.8562","name":"NVIDIA 3D VISION","length":1,toString: function () {return "[object Plugin]";}},"8":{"0":{"description":"JPEG-based stereo image","enabledPlugin":[{}],"suffixes":"jps","type":"image/jps"},"1":{"description":"PNG-based stereo image","enabledPlugin":[{}],"suffixes":"pns","type":"image/pns"},"2":{"description":"Multi-Picture Format image","enabledPlugin":[{}],"suffixes":"mpo","type":"image/mpo"},"image/jps":{"description":"JPEG-based stereo image","enabledPlugin":[{}],"suffixes":"jps","type":"image/jps"},"image/pns":{"description":"PNG-based stereo image","enabledPlugin":[{}],"suffixes":"pns","type":"image/pns"},"image/mpo":{"description":"Multi-Picture Format image","enabledPlugin":[{}],"suffixes":"mpo","type":"image/mpo"},"item":[""],"namedItem":[""],"description":"NVIDIA 3D Vision plugin for Mozilla browsers","filename":"npnv3dv.dll","version":"7.17.12.8562","name":"NVIDIA 3D Vision","length":3,toString: function () {return "[object Plugin]";}},"9":{"0":{"description":"Adobe Flash movie","enabledPlugin":[{}],"suffixes":"swf","type":"application/x-shockwave-flash"},"1":{"description":"FutureSplash movie","enabledPlugin":[{}],"suffixes":"spl","type":"application/futuresplash"},"application/x-shockwave-flash":{"description":"Adobe Flash movie","enabledPlugin":[{}],"suffixes":"swf","type":"application/x-shockwave-flash"},"application/futuresplash":{"description":"FutureSplash movie","enabledPlugin":[{}],"suffixes":"spl","type":"application/futuresplash"},"item":[""],"namedItem":[""],"description":"Shockwave Flash 23.0 r0","filename":"NPSWF32_23_0_0_185.dll","version":"23.0.0.185","name":"Shockwave Flash","length":2,toString: function () {return "[object Plugin]";}},"10":{"0":{"description":"Shockwave Movie","enabledPlugin":[{}],"suffixes":"dir,dxr,dcr","type":"application/x-director"},"application/x-director":{"description":"Shockwave Movie","enabledPlugin":[{}],"suffixes":"dir,dxr,dcr","type":"application/x-director"},"item":[""],"namedItem":[""],"description":"Adobe Shockwave for Director Netscape plug-in, version 11.6.5.635","filename":"np32dsw.dll","version":"11.6.5.635","name":"Shockwave for Director","length":1,toString: function () {return "[object Plugin]";}},"360 Total Security":{"0":{"description":"nptswp.dll","enabledPlugin":[{}],"suffixes":"","type":"application/x-nptswp"},"application/x-nptswp":{"description":"nptswp.dll","enabledPlugin":[{}],"suffixes":"","type":"application/x-nptswp"},"item":[""],"namedItem":[""],"description":"360 Total Security","filename":"nptswp.dll","version":"6.0.0.1004","name":"360 Total Security","length":1,toString: function () {return "[object Plugin]";}},"Adobe Acrobat":{"0":{"description":"Acrobat Portable Document Format","enabledPlugin":[{}],"suffixes":"pdf","type":"application/pdf"},"1":{"description":"Adobe PDF in XML Format","enabledPlugin":[{}],"suffixes":"pdfxml","type":"application/vnd.adobe.pdfxml"},"2":{"description":"Adobe PDF in XML Format","enabledPlugin":[{}],"suffixes":"mars","type":"application/vnd.adobe.x-mars"},"3":{"description":"Acrobat Forms Data Format","enabledPlugin":[{}],"suffixes":"fdf","type":"application/vnd.fdf"},"4":{"description":"XML Version of Acrobat Forms Data Format","enabledPlugin":[{}],"suffixes":"xfdf","type":"application/vnd.adobe.xfdf"},"5":{"description":" Acrobat XML Data Package","enabledPlugin":[{}],"suffixes":"xdp","type":"application/vnd.adobe.xdp+xml"},"6":{"description":"Adobe FormFlow99 Data File","enabledPlugin":[{}],"suffixes":"xfd","type":"application/vnd.adobe.xfd+xml"},"application/pdf":{"description":"Acrobat Portable Document Format","enabledPlugin":[{}],"suffixes":"pdf","type":"application/pdf"},"application/vnd.adobe.pdfxml":{"description":"Adobe PDF in XML Format","enabledPlugin":[{}],"suffixes":"pdfxml","type":"application/vnd.adobe.pdfxml"},"application/vnd.adobe.x-mars":{"description":"Adobe PDF in XML Format","enabledPlugin":[{}],"suffixes":"mars","type":"application/vnd.adobe.x-mars"},"application/vnd.fdf":{"description":"Acrobat Forms Data Format","enabledPlugin":[{}],"suffixes":"fdf","type":"application/vnd.fdf"},"application/vnd.adobe.xfdf":{"description":"XML Version of Acrobat Forms Data Format","enabledPlugin":[{}],"suffixes":"xfdf","type":"application/vnd.adobe.xfdf"},"application/vnd.adobe.xdp+xml":{"description":" Acrobat XML Data Package","enabledPlugin":[{}],"suffixes":"xdp","type":"application/vnd.adobe.xdp+xml"},"application/vnd.adobe.xfd+xml":{"description":"Adobe FormFlow99 Data File","enabledPlugin":[{}],"suffixes":"xfd","type":"application/vnd.adobe.xfd+xml"},"item":[""],"namedItem":[""],"description":"Adobe PDF Plug-In For Firefox and Netscape 15.20.20039","filename":"nppdf32.dll","version":"15.20.20039.7108","name":"Adobe Acrobat","length":7,toString: function () {return "[object Plugin]";}},"Authorware Web Player":{"0":{"description":"Authorware","enabledPlugin":[{}],"suffixes":"aam","type":"application/x-authorware-map"},"application/x-authorware-map":{"description":"Authorware","enabledPlugin":[{}],"suffixes":"aam","type":"application/x-authorware-map"},"item":[""],"namedItem":[""],"description":"Macromedia Authorware Web Player Netscape plug-in, version 2004 ","filename":"np32asw.dll","version":"2004.0.0.1","name":"Authorware Web Player","length":1,toString: function () {return "[object Plugin]";}},"CANON iMAGE GATEWAY Album Plugin Utility for IJ":{"0":{"description":"npmigfpi.dll","enabledPlugin":[{}],"suffixes":"","type":"application/x-eppex-plugin-1"},"application/x-eppex-plugin-1":{"description":"npmigfpi.dll","enabledPlugin":[{}],"suffixes":"","type":"application/x-eppex-plugin-1"},"item":[""],"namedItem":[""],"description":"CANON iMAGE GATEWAY Album Plugin Utility Module for IJ","filename":"npmigfpi.dll","version":"5.0.0.0","name":"CANON iMAGE GATEWAY Album Plugin Utility for IJ","length":1,toString: function () {return "[object Plugin]";}},"Google Update":{"0":{"description":"","enabledPlugin":[{}],"suffixes":"","type":"application/x-vnd.google.update3webcontrol.3"},"1":{"description":"","enabledPlugin":[{}],"suffixes":"","type":"application/x-vnd.google.oneclickctrl.9"},"application/x-vnd.google.update3webcontrol.3":{"description":"","enabledPlugin":[{}],"suffixes":"","type":"application/x-vnd.google.update3webcontrol.3"},"application/x-vnd.google.oneclickctrl.9":{"description":"","enabledPlugin":[{}],"suffixes":"","type":"application/x-vnd.google.oneclickctrl.9"},"item":[""],"namedItem":[""],"description":"Google Update","filename":"npGoogleUpdate3.dll","version":"1.3.31.5","name":"Google Update","length":2,toString: function () {return "[object Plugin]";}},"Microsoft Office 2010":{"0":{"description":"14.0.4730.1010","enabledPlugin":[{}],"suffixes":"*","type":"application/x-msoffice14"},"application/x-msoffice14":{"description":"14.0.4730.1010","enabledPlugin":[{}],"suffixes":"*","type":"application/x-msoffice14"},"item":[""],"namedItem":[""],"description":"Office Authorization plug-in for NPAPI browsers","filename":"NPAUTHZ.DLL","version":"14.0.4730.1010","name":"Microsoft Office 2010","length":1,toString: function () {return "[object Plugin]";}},"NVIDIA 3D VISION":{"0":{"description":"npnv3dvstreaming","enabledPlugin":[{}],"suffixes":"rts","type":"application/mozilla-3dv-streaming-plugin"},"application/mozilla-3dv-streaming-plugin":{"description":"npnv3dvstreaming","enabledPlugin":[{}],"suffixes":"rts","type":"application/mozilla-3dv-streaming-plugin"},"item":[""],"namedItem":[""],"description":"NVIDIA 3D Vision Streaming plugin for Mozilla browsers","filename":"npnv3dvstreaming.dll","version":"7.17.12.8562","name":"NVIDIA 3D VISION","length":1,toString: function () {return "[object Plugin]";}},"NVIDIA 3D Vision":{"0":{"description":"JPEG-based stereo image","enabledPlugin":[{}],"suffixes":"jps","type":"image/jps"},"1":{"description":"PNG-based stereo image","enabledPlugin":[{}],"suffixes":"pns","type":"image/pns"},"2":{"description":"Multi-Picture Format image","enabledPlugin":[{}],"suffixes":"mpo","type":"image/mpo"},"image/jps":{"description":"JPEG-based stereo image","enabledPlugin":[{}],"suffixes":"jps","type":"image/jps"},"image/pns":{"description":"PNG-based stereo image","enabledPlugin":[{}],"suffixes":"pns","type":"image/pns"},"image/mpo":{"description":"Multi-Picture Format image","enabledPlugin":[{}],"suffixes":"mpo","type":"image/mpo"},"item":[""],"namedItem":[""],"description":"NVIDIA 3D Vision plugin for Mozilla browsers","filename":"npnv3dv.dll","version":"7.17.12.8562","name":"NVIDIA 3D Vision","length":3,toString: function () {return "[object Plugin]";}},"Shockwave Flash":{"0":{"description":"Adobe Flash movie","enabledPlugin":[{}],"suffixes":"swf","type":"application/x-shockwave-flash"},"1":{"description":"FutureSplash movie","enabledPlugin":[{}],"suffixes":"spl","type":"application/futuresplash"},"application/x-shockwave-flash":{"description":"Adobe Flash movie","enabledPlugin":[{}],"suffixes":"swf","type":"application/x-shockwave-flash"},"application/futuresplash":{"description":"FutureSplash movie","enabledPlugin":[{}],"suffixes":"spl","type":"application/futuresplash"},"item":[""],"namedItem":[""],"description":"Shockwave Flash 23.0 r0","filename":"NPSWF32_23_0_0_185.dll","version":"23.0.0.185","name":"Shockwave Flash","length":2,toString: function () {return "[object Plugin]";}},"Shockwave for Director":{"0":{"description":"Shockwave Movie","enabledPlugin":[{}],"suffixes":"dir,dxr,dcr","type":"application/x-director"},"application/x-director":{"description":"Shockwave Movie","enabledPlugin":[{}],"suffixes":"dir,dxr,dcr","type":"application/x-director"},"item":[""],"namedItem":[""],"description":"Adobe Shockwave for Director Netscape plug-in, version 11.6.5.635","filename":"np32dsw.dll","version":"11.6.5.635","name":"Shockwave for Director","length":1,toString: function () {return "[object Plugin]";}},"item":{ toString : function () { return "function item() {    [native code]}";}},"namedItem":{ toString : function () { return "function namedItem() {    [native code]}";}},"refresh":{ toString : function () { return "function refresh() {    [native code]}";}},"length":11},"window.navigator.mimeTypes":{"0":{"description":"FutureSplash movie","enabledPlugin":{"0":[{}],"1":[{}],"application/x-shockwave-flash":[{}],"application/futuresplash":[{}],"item":"","namedItem":"","description":"Shockwave Flash 23.0 r0","filename":"NPSWF32_23_0_0_185.dll","version":"23.0.0.185","name":"Shockwave Flash","length":2},"suffixes":"spl","type":"application/futuresplash",toString: function () {return "[object MimeType]";}},"1":{"description":"npnv3dvstreaming","enabledPlugin":{"0":[{}],"application/mozilla-3dv-streaming-plugin":[{}],"item":"","namedItem":"","description":"NVIDIA 3D Vision Streaming plugin for Mozilla browsers","filename":"npnv3dvstreaming.dll","version":"7.17.12.8562","name":"NVIDIA 3D VISION","length":1},"suffixes":"rts","type":"application/mozilla-3dv-streaming-plugin",toString: function () {return "[object MimeType]";}},"2":{"description":"Acrobat Portable Document Format","enabledPlugin":{"0":[{}],"1":[{}],"2":[{}],"3":[{}],"4":[{}],"5":[{}],"6":[{}],"application/pdf":[{}],"application/vnd.adobe.pdfxml":[{}],"application/vnd.adobe.x-mars":[{}],"application/vnd.fdf":[{}],"application/vnd.adobe.xfdf":[{}],"application/vnd.adobe.xdp+xml":[{}],"application/vnd.adobe.xfd+xml":[{}],"item":"","namedItem":"","description":"Adobe PDF Plug-In For Firefox and Netscape 15.20.20039","filename":"nppdf32.dll","version":"15.20.20039.7108","name":"Adobe Acrobat","length":7},"suffixes":"pdf","type":"application/pdf",toString: function () {return "[object MimeType]";}},"3":{"description":"Adobe PDF in XML Format","enabledPlugin":{"0":[{}],"1":[{}],"2":[{}],"3":[{}],"4":[{}],"5":[{}],"6":[{}],"application/pdf":[{}],"application/vnd.adobe.pdfxml":[{}],"application/vnd.adobe.x-mars":[{}],"application/vnd.fdf":[{}],"application/vnd.adobe.xfdf":[{}],"application/vnd.adobe.xdp+xml":[{}],"application/vnd.adobe.xfd+xml":[{}],"item":"","namedItem":"","description":"Adobe PDF Plug-In For Firefox and Netscape 15.20.20039","filename":"nppdf32.dll","version":"15.20.20039.7108","name":"Adobe Acrobat","length":7},"suffixes":"pdfxml","type":"application/vnd.adobe.pdfxml",toString: function () {return "[object MimeType]";}},"4":{"description":"Adobe PDF in XML Format","enabledPlugin":{"0":[{}],"1":[{}],"2":[{}],"3":[{}],"4":[{}],"5":[{}],"6":[{}],"application/pdf":[{}],"application/vnd.adobe.pdfxml":[{}],"application/vnd.adobe.x-mars":[{}],"application/vnd.fdf":[{}],"application/vnd.adobe.xfdf":[{}],"application/vnd.adobe.xdp+xml":[{}],"application/vnd.adobe.xfd+xml":[{}],"item":"","namedItem":"","description":"Adobe PDF Plug-In For Firefox and Netscape 15.20.20039","filename":"nppdf32.dll","version":"15.20.20039.7108","name":"Adobe Acrobat","length":7},"suffixes":"mars","type":"application/vnd.adobe.x-mars",toString: function () {return "[object MimeType]";}},"5":{"description":" Acrobat XML Data Package","enabledPlugin":{"0":[{}],"1":[{}],"2":[{}],"3":[{}],"4":[{}],"5":[{}],"6":[{}],"application/pdf":[{}],"application/vnd.adobe.pdfxml":[{}],"application/vnd.adobe.x-mars":[{}],"application/vnd.fdf":[{}],"application/vnd.adobe.xfdf":[{}],"application/vnd.adobe.xdp+xml":[{}],"application/vnd.adobe.xfd+xml":[{}],"item":"","namedItem":"","description":"Adobe PDF Plug-In For Firefox and Netscape 15.20.20039","filename":"nppdf32.dll","version":"15.20.20039.7108","name":"Adobe Acrobat","length":7},"suffixes":"xdp","type":"application/vnd.adobe.xdp+xml",toString: function () {return "[object MimeType]";}},"6":{"description":"Adobe FormFlow99 Data File","enabledPlugin":{"0":[{}],"1":[{}],"2":[{}],"3":[{}],"4":[{}],"5":[{}],"6":[{}],"application/pdf":[{}],"application/vnd.adobe.pdfxml":[{}],"application/vnd.adobe.x-mars":[{}],"application/vnd.fdf":[{}],"application/vnd.adobe.xfdf":[{}],"application/vnd.adobe.xdp+xml":[{}],"application/vnd.adobe.xfd+xml":[{}],"item":"","namedItem":"","description":"Adobe PDF Plug-In For Firefox and Netscape 15.20.20039","filename":"nppdf32.dll","version":"15.20.20039.7108","name":"Adobe Acrobat","length":7},"suffixes":"xfd","type":"application/vnd.adobe.xfd+xml",toString: function () {return "[object MimeType]";}},"7":{"description":"XML Version of Acrobat Forms Data Format","enabledPlugin":{"0":[{}],"1":[{}],"2":[{}],"3":[{}],"4":[{}],"5":[{}],"6":[{}],"application/pdf":[{}],"application/vnd.adobe.pdfxml":[{}],"application/vnd.adobe.x-mars":[{}],"application/vnd.fdf":[{}],"application/vnd.adobe.xfdf":[{}],"application/vnd.adobe.xdp+xml":[{}],"application/vnd.adobe.xfd+xml":[{}],"item":"","namedItem":"","description":"Adobe PDF Plug-In For Firefox and Netscape 15.20.20039","filename":"nppdf32.dll","version":"15.20.20039.7108","name":"Adobe Acrobat","length":7},"suffixes":"xfdf","type":"application/vnd.adobe.xfdf",toString: function () {return "[object MimeType]";}},"8":{"description":"Acrobat Forms Data Format","enabledPlugin":{"0":[{}],"1":[{}],"2":[{}],"3":[{}],"4":[{}],"5":[{}],"6":[{}],"application/pdf":[{}],"application/vnd.adobe.pdfxml":[{}],"application/vnd.adobe.x-mars":[{}],"application/vnd.fdf":[{}],"application/vnd.adobe.xfdf":[{}],"application/vnd.adobe.xdp+xml":[{}],"application/vnd.adobe.xfd+xml":[{}],"item":"","namedItem":"","description":"Adobe PDF Plug-In For Firefox and Netscape 15.20.20039","filename":"nppdf32.dll","version":"15.20.20039.7108","name":"Adobe Acrobat","length":7},"suffixes":"fdf","type":"application/vnd.fdf",toString: function () {return "[object MimeType]";}},"9":{"description":"Authorware","enabledPlugin":{"0":[{}],"application/x-authorware-map":[{}],"item":"","namedItem":"","description":"Macromedia Authorware Web Player Netscape plug-in, version 2004 ","filename":"np32asw.dll","version":"2004.0.0.1","name":"Authorware Web Player","length":1},"suffixes":"aam","type":"application/x-authorware-map",toString: function () {return "[object MimeType]";}},"10":{"description":"Shockwave Movie","enabledPlugin":{"0":[{}],"application/x-director":[{}],"item":"","namedItem":"","description":"Adobe Shockwave for Director Netscape plug-in, version 11.6.5.635","filename":"np32dsw.dll","version":"11.6.5.635","name":"Shockwave for Director","length":1},"suffixes":"dir,dxr,dcr","type":"application/x-director",toString: function () {return "[object MimeType]";}},"11":{"description":"npmigfpi.dll","enabledPlugin":{"0":[{}],"application/x-eppex-plugin-1":[{}],"item":"","namedItem":"","description":"CANON iMAGE GATEWAY Album Plugin Utility Module for IJ","filename":"npmigfpi.dll","version":"5.0.0.0","name":"CANON iMAGE GATEWAY Album Plugin Utility for IJ","length":1},"suffixes":"","type":"application/x-eppex-plugin-1",toString: function () {return "[object MimeType]";}},"12":{"description":"14.0.4730.1010","enabledPlugin":{"0":[{}],"application/x-msoffice14":[{}],"item":"","namedItem":"","description":"Office Authorization plug-in for NPAPI browsers","filename":"NPAUTHZ.DLL","version":"14.0.4730.1010","name":"Microsoft Office 2010","length":1},"suffixes":"*","type":"application/x-msoffice14",toString: function () {return "[object MimeType]";}},"13":{"description":"nptswp.dll","enabledPlugin":{"0":[{}],"application/x-nptswp":[{}],"item":"","namedItem":"","description":"360 Total Security","filename":"nptswp.dll","version":"6.0.0.1004","name":"360 Total Security","length":1},"suffixes":"","type":"application/x-nptswp",toString: function () {return "[object MimeType]";}},"14":{"description":"SharePoint Plug-in for Firefox","enabledPlugin":{"0":[{}],"application/x-sharepoint":[{}],"item":"","namedItem":"","description":"The plug-in allows you to open and edit files using Microsoft Office applications","filename":"NPSPWRAP.DLL","version":"14.0.4761.1000","name":"Microsoft Office 2010","length":1},"suffixes":"","type":"application/x-sharepoint",toString: function () {return "[object MimeType]";}},"15":{"description":"Adobe Flash movie","enabledPlugin":{"0":[{}],"1":[{}],"application/x-shockwave-flash":[{}],"application/futuresplash":[{}],"item":"","namedItem":"","description":"Shockwave Flash 23.0 r0","filename":"NPSWF32_23_0_0_185.dll","version":"23.0.0.185","name":"Shockwave Flash","length":2},"suffixes":"swf","type":"application/x-shockwave-flash",toString: function () {return "[object MimeType]";}},"16":{"description":"","enabledPlugin":{"0":[{}],"1":[{}],"application/x-vnd.google.update3webcontrol.3":[{}],"application/x-vnd.google.oneclickctrl.9":[{}],"item":"","namedItem":"","description":"Google Update","filename":"npGoogleUpdate3.dll","version":"1.3.31.5","name":"Google Update","length":2},"suffixes":"","type":"application/x-vnd.google.oneclickctrl.9",toString: function () {return "[object MimeType]";}},"17":{"description":"","enabledPlugin":{"0":[{}],"1":[{}],"application/x-vnd.google.update3webcontrol.3":[{}],"application/x-vnd.google.oneclickctrl.9":[{}],"item":"","namedItem":"","description":"Google Update","filename":"npGoogleUpdate3.dll","version":"1.3.31.5","name":"Google Update","length":2},"suffixes":"","type":"application/x-vnd.google.update3webcontrol.3",toString: function () {return "[object MimeType]";}},"18":{"description":"JPEG-based stereo image","enabledPlugin":{"0":[{}],"1":[{}],"2":[{}],"image/jps":[{}],"image/pns":[{}],"image/mpo":[{}],"item":"","namedItem":"","description":"NVIDIA 3D Vision plugin for Mozilla browsers","filename":"npnv3dv.dll","version":"7.17.12.8562","name":"NVIDIA 3D Vision","length":3},"suffixes":"jps","type":"image/jps",toString: function () {return "[object MimeType]";}},"19":{"description":"Multi-Picture Format image","enabledPlugin":{"0":[{}],"1":[{}],"2":[{}],"image/jps":[{}],"image/pns":[{}],"image/mpo":[{}],"item":"","namedItem":"","description":"NVIDIA 3D Vision plugin for Mozilla browsers","filename":"npnv3dv.dll","version":"7.17.12.8562","name":"NVIDIA 3D Vision","length":3},"suffixes":"mpo","type":"image/mpo",toString: function () {return "[object MimeType]";}},"20":{"description":"PNG-based stereo image","enabledPlugin":{"0":[{}],"1":[{}],"2":[{}],"image/jps":[{}],"image/pns":[{}],"image/mpo":[{}],"item":"","namedItem":"","description":"NVIDIA 3D Vision plugin for Mozilla browsers","filename":"npnv3dv.dll","version":"7.17.12.8562","name":"NVIDIA 3D Vision","length":3},"suffixes":"pns","type":"image/pns",toString: function () {return "[object MimeType]";}},"application/futuresplash":{"description":"FutureSplash movie","enabledPlugin":{"0":[{}],"1":[{}],"application/x-shockwave-flash":[{}],"application/futuresplash":[{}],"item":"","namedItem":"","description":"Shockwave Flash 23.0 r0","filename":"NPSWF32_23_0_0_185.dll","version":"23.0.0.185","name":"Shockwave Flash","length":2},"suffixes":"spl","type":"application/futuresplash",toString: function () {return "[object MimeType]";}},"application/mozilla-3dv-streaming-plugin":{"description":"npnv3dvstreaming","enabledPlugin":{"0":[{}],"application/mozilla-3dv-streaming-plugin":[{}],"item":"","namedItem":"","description":"NVIDIA 3D Vision Streaming plugin for Mozilla browsers","filename":"npnv3dvstreaming.dll","version":"7.17.12.8562","name":"NVIDIA 3D VISION","length":1},"suffixes":"rts","type":"application/mozilla-3dv-streaming-plugin",toString: function () {return "[object MimeType]";}},"application/pdf":{"description":"Acrobat Portable Document Format","enabledPlugin":{"0":[{}],"1":[{}],"2":[{}],"3":[{}],"4":[{}],"5":[{}],"6":[{}],"application/pdf":[{}],"application/vnd.adobe.pdfxml":[{}],"application/vnd.adobe.x-mars":[{}],"application/vnd.fdf":[{}],"application/vnd.adobe.xfdf":[{}],"application/vnd.adobe.xdp+xml":[{}],"application/vnd.adobe.xfd+xml":[{}],"item":"","namedItem":"","description":"Adobe PDF Plug-In For Firefox and Netscape 15.20.20039","filename":"nppdf32.dll","version":"15.20.20039.7108","name":"Adobe Acrobat","length":7},"suffixes":"pdf","type":"application/pdf",toString: function () {return "[object MimeType]";}},"application/vnd.adobe.pdfxml":{"description":"Adobe PDF in XML Format","enabledPlugin":{"0":[{}],"1":[{}],"2":[{}],"3":[{}],"4":[{}],"5":[{}],"6":[{}],"application/pdf":[{}],"application/vnd.adobe.pdfxml":[{}],"application/vnd.adobe.x-mars":[{}],"application/vnd.fdf":[{}],"application/vnd.adobe.xfdf":[{}],"application/vnd.adobe.xdp+xml":[{}],"application/vnd.adobe.xfd+xml":[{}],"item":"","namedItem":"","description":"Adobe PDF Plug-In For Firefox and Netscape 15.20.20039","filename":"nppdf32.dll","version":"15.20.20039.7108","name":"Adobe Acrobat","length":7},"suffixes":"pdfxml","type":"application/vnd.adobe.pdfxml",toString: function () {return "[object MimeType]";}},"application/vnd.adobe.x-mars":{"description":"Adobe PDF in XML Format","enabledPlugin":{"0":[{}],"1":[{}],"2":[{}],"3":[{}],"4":[{}],"5":[{}],"6":[{}],"application/pdf":[{}],"application/vnd.adobe.pdfxml":[{}],"application/vnd.adobe.x-mars":[{}],"application/vnd.fdf":[{}],"application/vnd.adobe.xfdf":[{}],"application/vnd.adobe.xdp+xml":[{}],"application/vnd.adobe.xfd+xml":[{}],"item":"","namedItem":"","description":"Adobe PDF Plug-In For Firefox and Netscape 15.20.20039","filename":"nppdf32.dll","version":"15.20.20039.7108","name":"Adobe Acrobat","length":7},"suffixes":"mars","type":"application/vnd.adobe.x-mars",toString: function () {return "[object MimeType]";}},"application/vnd.adobe.xdp+xml":{"description":" Acrobat XML Data Package","enabledPlugin":{"0":[{}],"1":[{}],"2":[{}],"3":[{}],"4":[{}],"5":[{}],"6":[{}],"application/pdf":[{}],"application/vnd.adobe.pdfxml":[{}],"application/vnd.adobe.x-mars":[{}],"application/vnd.fdf":[{}],"application/vnd.adobe.xfdf":[{}],"application/vnd.adobe.xdp+xml":[{}],"application/vnd.adobe.xfd+xml":[{}],"item":"","namedItem":"","description":"Adobe PDF Plug-In For Firefox and Netscape 15.20.20039","filename":"nppdf32.dll","version":"15.20.20039.7108","name":"Adobe Acrobat","length":7},"suffixes":"xdp","type":"application/vnd.adobe.xdp+xml",toString: function () {return "[object MimeType]";}},"application/vnd.adobe.xfd+xml":{"description":"Adobe FormFlow99 Data File","enabledPlugin":{"0":[{}],"1":[{}],"2":[{}],"3":[{}],"4":[{}],"5":[{}],"6":[{}],"application/pdf":[{}],"application/vnd.adobe.pdfxml":[{}],"application/vnd.adobe.x-mars":[{}],"application/vnd.fdf":[{}],"application/vnd.adobe.xfdf":[{}],"application/vnd.adobe.xdp+xml":[{}],"application/vnd.adobe.xfd+xml":[{}],"item":"","namedItem":"","description":"Adobe PDF Plug-In For Firefox and Netscape 15.20.20039","filename":"nppdf32.dll","version":"15.20.20039.7108","name":"Adobe Acrobat","length":7},"suffixes":"xfd","type":"application/vnd.adobe.xfd+xml",toString: function () {return "[object MimeType]";}},"application/vnd.adobe.xfdf":{"description":"XML Version of Acrobat Forms Data Format","enabledPlugin":{"0":[{}],"1":[{}],"2":[{}],"3":[{}],"4":[{}],"5":[{}],"6":[{}],"application/pdf":[{}],"application/vnd.adobe.pdfxml":[{}],"application/vnd.adobe.x-mars":[{}],"application/vnd.fdf":[{}],"application/vnd.adobe.xfdf":[{}],"application/vnd.adobe.xdp+xml":[{}],"application/vnd.adobe.xfd+xml":[{}],"item":"","namedItem":"","description":"Adobe PDF Plug-In For Firefox and Netscape 15.20.20039","filename":"nppdf32.dll","version":"15.20.20039.7108","name":"Adobe Acrobat","length":7},"suffixes":"xfdf","type":"application/vnd.adobe.xfdf",toString: function () {return "[object MimeType]";}},"application/vnd.fdf":{"description":"Acrobat Forms Data Format","enabledPlugin":{"0":[{}],"1":[{}],"2":[{}],"3":[{}],"4":[{}],"5":[{}],"6":[{}],"application/pdf":[{}],"application/vnd.adobe.pdfxml":[{}],"application/vnd.adobe.x-mars":[{}],"application/vnd.fdf":[{}],"application/vnd.adobe.xfdf":[{}],"application/vnd.adobe.xdp+xml":[{}],"application/vnd.adobe.xfd+xml":[{}],"item":"","namedItem":"","description":"Adobe PDF Plug-In For Firefox and Netscape 15.20.20039","filename":"nppdf32.dll","version":"15.20.20039.7108","name":"Adobe Acrobat","length":7},"suffixes":"fdf","type":"application/vnd.fdf",toString: function () {return "[object MimeType]";}},"application/x-authorware-map":{"description":"Authorware","enabledPlugin":{"0":[{}],"application/x-authorware-map":[{}],"item":"","namedItem":"","description":"Macromedia Authorware Web Player Netscape plug-in, version 2004 ","filename":"np32asw.dll","version":"2004.0.0.1","name":"Authorware Web Player","length":1},"suffixes":"aam","type":"application/x-authorware-map",toString: function () {return "[object MimeType]";}},"application/x-director":{"description":"Shockwave Movie","enabledPlugin":{"0":[{}],"application/x-director":[{}],"item":"","namedItem":"","description":"Adobe Shockwave for Director Netscape plug-in, version 11.6.5.635","filename":"np32dsw.dll","version":"11.6.5.635","name":"Shockwave for Director","length":1},"suffixes":"dir,dxr,dcr","type":"application/x-director",toString: function () {return "[object MimeType]";}},"application/x-eppex-plugin-1":{"description":"npmigfpi.dll","enabledPlugin":{"0":[{}],"application/x-eppex-plugin-1":[{}],"item":"","namedItem":"","description":"CANON iMAGE GATEWAY Album Plugin Utility Module for IJ","filename":"npmigfpi.dll","version":"5.0.0.0","name":"CANON iMAGE GATEWAY Album Plugin Utility for IJ","length":1},"suffixes":"","type":"application/x-eppex-plugin-1",toString: function () {return "[object MimeType]";}},"application/x-msoffice14":{"description":"14.0.4730.1010","enabledPlugin":{"0":[{}],"application/x-msoffice14":[{}],"item":"","namedItem":"","description":"Office Authorization plug-in for NPAPI browsers","filename":"NPAUTHZ.DLL","version":"14.0.4730.1010","name":"Microsoft Office 2010","length":1},"suffixes":"*","type":"application/x-msoffice14",toString: function () {return "[object MimeType]";}},"application/x-nptswp":{"description":"nptswp.dll","enabledPlugin":{"0":[{}],"application/x-nptswp":[{}],"item":"","namedItem":"","description":"360 Total Security","filename":"nptswp.dll","version":"6.0.0.1004","name":"360 Total Security","length":1},"suffixes":"","type":"application/x-nptswp",toString: function () {return "[object MimeType]";}},"application/x-sharepoint":{"description":"SharePoint Plug-in for Firefox","enabledPlugin":{"0":[{}],"application/x-sharepoint":[{}],"item":"","namedItem":"","description":"The plug-in allows you to open and edit files using Microsoft Office applications","filename":"NPSPWRAP.DLL","version":"14.0.4761.1000","name":"Microsoft Office 2010","length":1},"suffixes":"","type":"application/x-sharepoint",toString: function () {return "[object MimeType]";}},"application/x-shockwave-flash":{"description":"Adobe Flash movie","enabledPlugin":{"0":[{}],"1":[{}],"application/x-shockwave-flash":[{}],"application/futuresplash":[{}],"item":"","namedItem":"","description":"Shockwave Flash 23.0 r0","filename":"NPSWF32_23_0_0_185.dll","version":"23.0.0.185","name":"Shockwave Flash","length":2},"suffixes":"swf","type":"application/x-shockwave-flash",toString: function () {return "[object MimeType]";}},"application/x-vnd.google.oneclickctrl.9":{"description":"","enabledPlugin":{"0":[{}],"1":[{}],"application/x-vnd.google.update3webcontrol.3":[{}],"application/x-vnd.google.oneclickctrl.9":[{}],"item":"","namedItem":"","description":"Google Update","filename":"npGoogleUpdate3.dll","version":"1.3.31.5","name":"Google Update","length":2},"suffixes":"","type":"application/x-vnd.google.oneclickctrl.9",toString: function () {return "[object MimeType]";}},"application/x-vnd.google.update3webcontrol.3":{"description":"","enabledPlugin":{"0":[{}],"1":[{}],"application/x-vnd.google.update3webcontrol.3":[{}],"application/x-vnd.google.oneclickctrl.9":[{}],"item":"","namedItem":"","description":"Google Update","filename":"npGoogleUpdate3.dll","version":"1.3.31.5","name":"Google Update","length":2},"suffixes":"","type":"application/x-vnd.google.update3webcontrol.3",toString: function () {return "[object MimeType]";}},"image/jps":{"description":"JPEG-based stereo image","enabledPlugin":{"0":[{}],"1":[{}],"2":[{}],"image/jps":[{}],"image/pns":[{}],"image/mpo":[{}],"item":"","namedItem":"","description":"NVIDIA 3D Vision plugin for Mozilla browsers","filename":"npnv3dv.dll","version":"7.17.12.8562","name":"NVIDIA 3D Vision","length":3},"suffixes":"jps","type":"image/jps",toString: function () {return "[object MimeType]";}},"image/mpo":{"description":"Multi-Picture Format image","enabledPlugin":{"0":[{}],"1":[{}],"2":[{}],"image/jps":[{}],"image/pns":[{}],"image/mpo":[{}],"item":"","namedItem":"","description":"NVIDIA 3D Vision plugin for Mozilla browsers","filename":"npnv3dv.dll","version":"7.17.12.8562","name":"NVIDIA 3D Vision","length":3},"suffixes":"mpo","type":"image/mpo",toString: function () {return "[object MimeType]";}},"image/pns":{"description":"PNG-based stereo image","enabledPlugin":{"0":[{}],"1":[{}],"2":[{}],"image/jps":[{}],"image/pns":[{}],"image/mpo":[{}],"item":"","namedItem":"","description":"NVIDIA 3D Vision plugin for Mozilla browsers","filename":"npnv3dv.dll","version":"7.17.12.8562","name":"NVIDIA 3D Vision","length":3},"suffixes":"pns","type":"image/pns",toString: function () {return "[object MimeType]";}},"item":{ toString : function () { return "function item() {    [native code]}";}},"namedItem":{ toString : function () { return "function namedItem() {    [native code]}";}},"length":21},"document":{}}