{"window.screen":{"mozLockOrientation":{toString: function () { return "function mozLockOrientation() {    [native code]}";}},"mozUnlockOrientation":{toString: function () { return "function mozUnlockOrientation() {    [native code]}";}},"availWidth":1366,"availHeight":728,"width":1366,"height":768,"colorDepth":24,"pixelDepth":24,"top":0,"left":0,"availTop":0,"availLeft":0,"mozOrientation":"landscape-primary","onmozorientationchange":null,"orientation":{toString: function () {return "[object ScreenOrientation]";},"lock":[""],"unlock":[""],"type":"landscape-primary","angle":0,"onchange":null,"addEventListener":[""],"removeEventListener":[""],"dispatchEvent":[""]},"addEventListener":{toString: function () { return "function addEventListener() {    [native code]}";}},"removeEventListener":{toString: function () { return "function removeEventListener() {    [native code]}";}},"dispatchEvent":{toString: function () { return "function dispatchEvent() {    [native code]}";}}},"window":{ "mozInnerScreenX":0,"mozInnerScreenY":162,"mozPaintCount":0,"onmozfullscreenchange":null,"onmozfullscreenerror":null,"onmozpointerlockchange":null,"onmozpointerlockerror":null,"RTCPeerConnection":{toString: function () {return "function RTCPeerConnection() { [native code] }";}},"RTCSessionDescription":{toString: function () {return "function RTCSessionDescription() { [native code] }";}},"MediaStreamTrack":{toString: function () {return "function MediaStreamTrack() { [native code] }";}},"indexedDB":{toString: function () {       return "[object indexedDB]";},"open":function () { return 0;}},"devicePixelRatio":1,"outerWidth":1382,"innerWidth":19,"innerHeight":19, "navigator": {"mozPay":null,"mozContacts":{toString: function () {return "[object ContactManager]";},"find":[""],"getAll":[""],"clear":[""],"save":[""],"remove":[""],"getRevision":[""],"getCount":[""],"oncontactchange":null,"addEventListener":[""],"removeEventListener":[""],"dispatchEvent":[""]},"mozApps":{toString: function () {return "[object DOMApplicationsRegistry]";},"install":[""],"installPackage":[""],"getSelf":[""],"getInstalled":[""],"checkInstalled":[""],"getAdditionalLanguages":[""],"getLocalizationResource":[""]},"getBattery":{toString: function () { return "function getBattery() {    [native code]}";}},"vibrate":{toString: function () { return "function vibrate() {    [native code]}";}},"javaEnabled":function javaEnabled() {return true;},"getGamepads":{toString: function () { return "function getGamepads() {    [native code]}";}},"mozGetUserMedia":{toString: function () { return "function mozGetUserMedia() {    [native code]}";}},"requestMediaKeySystemAccess":{toString: function () { return "function requestMediaKeySystemAccess() {    [native code]}";}},"registerProtocolHandler":{toString: function () { return "function registerProtocolHandler() {    [native code]}";}},"registerContentHandler":{toString: function () { return "function registerContentHandler() {    [native code]}";}},"taintEnabled":{toString: function () { return "function taintEnabled() {    [native code]}";}},"mimeTypes":{toString: function () {       return "[object MimeTypeArray]";}},"plugins":{toString: function () {       return "[object PluginArray]";}},"doNotTrack":"unspecified","battery":{toString: function () {return "[object BatteryManager]";},"charging":true,"chargingTime":null,"dischargingTime":null,"level":0.6,"onchargingchange":null,"onchargingtimechange":null,"ondischargingtimechange":null,"onlevelchange":null,"addEventListener":[""],"removeEventListener":[""],"dispatchEvent":[""]},"oscpu":"Windows NT 10.0; WOW64","vendor":"","vendorSub":"","productSub":"20100101","cookieEnabled":true,"buildID":"20160210153822","mediaDevices":{toString: function () {return "[object MediaDevices]";},"getSupportedConstraints":[""],"enumerateDevices":[""],"getUserMedia":[""],"addEventListener":[""],"removeEventListener":[""],"dispatchEvent":[""]},"serviceWorker":{toString: function () {return "[object ServiceWorkerContainer]";},"controller":null,"register":[""],"getRegistration":[""],"getRegistrations":[""],"ready":{},"oncontrollerchange":null,"onerror":null,"onmessage":null,"addEventListener":[""],"removeEventListener":[""],"dispatchEvent":[""]},"geolocation":{toString: function () {return "[object Geolocation]";},"getCurrentPosition":[""],"watchPosition":[""],"clearWatch":[""]},"appCodeName":"Mozilla","appName":"Netscape","appVersion":"5.0 (Windows)","platform":"Win32","userAgent":"Mozilla/5.0 (Windows NT 10.0; WOW64; rv:57.0) Gecko/20100101 Firefox/57.0","product":"Gecko","language":"en-US","languages":["en-US","en"],"onLine":true}},"window.navigator.plugins":{"0":{toString: function () {return "[object Plugin]";},"0":{"description":"npIntelWebAPIupdater-2-0","enabledPlugin":{},"suffixes":"intel_webapi_updater-2-0","type":"application/x-vnd-intel-webapi-updater"},"application/x-vnd-intel-webapi-updater":{"description":"npIntelWebAPIupdater-2-0","enabledPlugin":{},"suffixes":"intel_webapi_updater-2-0","type":"application/x-vnd-intel-webapi-updater"},"item":[""],"namedItem":[""],"description":"Intel web components updater - Installs and updates the Intel web components","filename":"npIntelWebAPIUpdater.dll","version":"4.0.68.0","name":"Intel® Identity Protection Technology","length":1},"1":{toString: function () {return "[object Plugin]";},"0":{"description":"npIntelWebAPIipt-3-5","enabledPlugin":{},"suffixes":"","type":"application/x-vnd-intel-webapi-ipt-4.0.68"},"application/x-vnd-intel-webapi-ipt-4.0.68":{"description":"npIntelWebAPIipt-3-5","enabledPlugin":{},"suffixes":"","type":"application/x-vnd-intel-webapi-ipt-4.0.68"},"item":[""],"namedItem":[""],"description":"Intel web components for Intel® Identity Protection Technology","filename":"npIntelWebAPIIPT.dll","version":"4.0.68.0","name":"Intel® Identity Protection Technology","length":1},"2":{toString: function () {return "[object Plugin]";},"0":{"description":"","enabledPlugin":{},"suffixes":"","type":"application/x-mfe-ipt"},"application/x-mfe-ipt":{"description":"","enabledPlugin":{},"suffixes":"","type":"application/x-mfe-ipt"},"item":[""],"namedItem":[""],"description":"McAfee MSC FF plugin DLL","filename":"npMcSnFFPl.dll","version":"14.0.6136.0","name":"McAfee SecurityCenter","length":1},"3":{toString: function () {return "[object Plugin]";},"0":{"description":"SharePoint Plug-in for Firefox","enabledPlugin":{},"suffixes":"","type":"application/x-sharepoint"},"1":{"description":"","enabledPlugin":{},"suffixes":"","type":"application/x-sharepoint-uc"},"application/x-sharepoint":{"description":"SharePoint Plug-in for Firefox","enabledPlugin":{},"suffixes":"","type":"application/x-sharepoint"},"application/x-sharepoint-uc":{"description":"","enabledPlugin":{},"suffixes":"","type":"application/x-sharepoint-uc"},"item":[""],"namedItem":[""],"description":"The plugin allows you to have a better experience with Microsoft SharePoint","filename":"NPSPWRAP.DLL","version":"16.0.6326.1026","name":"Microsoft Office 2016","length":2},"4":{toString: function () {return "[object Plugin]";},"0":{"description":"Adobe Flash movie","enabledPlugin":{},"suffixes":"swf","type":"application/x-shockwave-flash"},"1":{"description":"FutureSplash movie","enabledPlugin":{},"suffixes":"spl","type":"application/futuresplash"},"application/x-shockwave-flash":{"description":"Adobe Flash movie","enabledPlugin":{},"suffixes":"swf","type":"application/x-shockwave-flash"},"application/futuresplash":{"description":"FutureSplash movie","enabledPlugin":{},"suffixes":"spl","type":"application/futuresplash"},"item":[""],"namedItem":[""],"description":"Shockwave Flash 20.0 r0","filename":"NPSWF32_20_0_0_306.dll","version":"20.0.0.306","name":"Shockwave Flash","length":2},"Intel® Identity Protection Technology":{toString: function () {return "[object Plugin]";},"0":{"description":"npIntelWebAPIupdater-2-0","enabledPlugin":{},"suffixes":"intel_webapi_updater-2-0","type":"application/x-vnd-intel-webapi-updater"},"application/x-vnd-intel-webapi-updater":{"description":"npIntelWebAPIupdater-2-0","enabledPlugin":{},"suffixes":"intel_webapi_updater-2-0","type":"application/x-vnd-intel-webapi-updater"},"item":[""],"namedItem":[""],"description":"Intel web components updater - Installs and updates the Intel web components","filename":"npIntelWebAPIUpdater.dll","version":"4.0.68.0","name":"Intel® Identity Protection Technology","length":1},"McAfee SecurityCenter":{toString: function () {return "[object Plugin]";},"0":{"description":"","enabledPlugin":{},"suffixes":"","type":"application/x-mfe-ipt"},"application/x-mfe-ipt":{"description":"","enabledPlugin":{},"suffixes":"","type":"application/x-mfe-ipt"},"item":[""],"namedItem":[""],"description":"McAfee MSC FF plugin DLL","filename":"npMcSnFFPl.dll","version":"14.0.6136.0","name":"McAfee SecurityCenter","length":1},"Microsoft Office 2016":{toString: function () {return "[object Plugin]";},"0":{"description":"SharePoint Plug-in for Firefox","enabledPlugin":{},"suffixes":"","type":"application/x-sharepoint"},"1":{"description":"","enabledPlugin":{},"suffixes":"","type":"application/x-sharepoint-uc"},"application/x-sharepoint":{"description":"SharePoint Plug-in for Firefox","enabledPlugin":{},"suffixes":"","type":"application/x-sharepoint"},"application/x-sharepoint-uc":{"description":"","enabledPlugin":{},"suffixes":"","type":"application/x-sharepoint-uc"},"item":[""],"namedItem":[""],"description":"The plugin allows you to have a better experience with Microsoft SharePoint","filename":"NPSPWRAP.DLL","version":"16.0.6326.1026","name":"Microsoft Office 2016","length":2},"Shockwave Flash":{toString: function () {return "[object Plugin]";},"0":{"description":"Adobe Flash movie","enabledPlugin":{},"suffixes":"swf","type":"application/x-shockwave-flash"},"1":{"description":"FutureSplash movie","enabledPlugin":{},"suffixes":"spl","type":"application/futuresplash"},"application/x-shockwave-flash":{"description":"Adobe Flash movie","enabledPlugin":{},"suffixes":"swf","type":"application/x-shockwave-flash"},"application/futuresplash":{"description":"FutureSplash movie","enabledPlugin":{},"suffixes":"spl","type":"application/futuresplash"},"item":[""],"namedItem":[""],"description":"Shockwave Flash 20.0 r0","filename":"NPSWF32_20_0_0_306.dll","version":"20.0.0.306","name":"Shockwave Flash","length":2},"item":{toString: function () { return "function item() {    [native code]}";}},"namedItem":{toString: function () { return "function namedItem() {    [native code]}";}},"refresh": function () { return "function refresh() {    [native code]}";},"length":5},"window.navigator.mimeTypes":{"0":{toString: function () {return "[object MimeType]";},"description":"FutureSplash movie","enabledPlugin":{"0":{},"1":{},"application/x-shockwave-flash":{},"application/futuresplash":{},"item":"","namedItem":"","description":"Shockwave Flash 20.0 r0","filename":"NPSWF32_20_0_0_306.dll","version":"20.0.0.306","name":"Shockwave Flash","length":2},"suffixes":"spl","type":"application/futuresplash"},"1":{toString: function () {return "[object MimeType]";},"description":"","enabledPlugin":{"0":{},"application/x-mfe-ipt":{},"item":"","namedItem":"","description":"McAfee MSC FF plugin DLL","filename":"npMcSnFFPl.dll","version":"14.0.6136.0","name":"McAfee SecurityCenter","length":1},"suffixes":"","type":"application/x-mfe-ipt"},"2":{toString: function () {return "[object MimeType]";},"description":"SharePoint Plug-in for Firefox","enabledPlugin":{"0":{},"1":{},"application/x-sharepoint":{},"application/x-sharepoint-uc":{},"item":"","namedItem":"","description":"The plugin allows you to have a better experience with Microsoft SharePoint","filename":"NPSPWRAP.DLL","version":"16.0.6326.1026","name":"Microsoft Office 2016","length":2},"suffixes":"","type":"application/x-sharepoint"},"3":{toString: function () {return "[object MimeType]";},"description":"","enabledPlugin":{"0":{},"1":{},"application/x-sharepoint":{},"application/x-sharepoint-uc":{},"item":"","namedItem":"","description":"The plugin allows you to have a better experience with Microsoft SharePoint","filename":"NPSPWRAP.DLL","version":"16.0.6326.1026","name":"Microsoft Office 2016","length":2},"suffixes":"","type":"application/x-sharepoint-uc"},"4":{toString: function () {return "[object MimeType]";},"description":"Adobe Flash movie","enabledPlugin":{"0":{},"1":{},"application/x-shockwave-flash":{},"application/futuresplash":{},"item":"","namedItem":"","description":"Shockwave Flash 20.0 r0","filename":"NPSWF32_20_0_0_306.dll","version":"20.0.0.306","name":"Shockwave Flash","length":2},"suffixes":"swf","type":"application/x-shockwave-flash"},"5":{toString: function () {return "[object MimeType]";},"description":"npIntelWebAPIipt-3-5","enabledPlugin":{"0":{},"application/x-vnd-intel-webapi-ipt-4.0.68":{},"item":"","namedItem":"","description":"Intel web components for Intel® Identity Protection Technology","filename":"npIntelWebAPIIPT.dll","version":"4.0.68.0","name":"Intel® Identity Protection Technology","length":1},"suffixes":"","type":"application/x-vnd-intel-webapi-ipt-4.0.68"},"6":{toString: function () {return "[object MimeType]";},"description":"npIntelWebAPIupdater-2-0","enabledPlugin":{"0":{},"application/x-vnd-intel-webapi-updater":{},"item":"","namedItem":"","description":"Intel web components updater - Installs and updates the Intel web components","filename":"npIntelWebAPIUpdater.dll","version":"4.0.68.0","name":"Intel® Identity Protection Technology","length":1},"suffixes":"intel_webapi_updater-2-0","type":"application/x-vnd-intel-webapi-updater"},"application/futuresplash":{toString: function () {return "[object MimeType]";},"description":"FutureSplash movie","enabledPlugin":{"0":{},"1":{},"application/x-shockwave-flash":{},"application/futuresplash":{},"item":"","namedItem":"","description":"Shockwave Flash 20.0 r0","filename":"NPSWF32_20_0_0_306.dll","version":"20.0.0.306","name":"Shockwave Flash","length":2},"suffixes":"spl","type":"application/futuresplash"},"application/x-mfe-ipt":{toString: function () {return "[object MimeType]";},"description":"","enabledPlugin":{"0":{},"application/x-mfe-ipt":{},"item":"","namedItem":"","description":"McAfee MSC FF plugin DLL","filename":"npMcSnFFPl.dll","version":"14.0.6136.0","name":"McAfee SecurityCenter","length":1},"suffixes":"","type":"application/x-mfe-ipt"},"application/x-sharepoint":{toString: function () {return "[object MimeType]";},"description":"SharePoint Plug-in for Firefox","enabledPlugin":{"0":{},"1":{},"application/x-sharepoint":{},"application/x-sharepoint-uc":{},"item":"","namedItem":"","description":"The plugin allows you to have a better experience with Microsoft SharePoint","filename":"NPSPWRAP.DLL","version":"16.0.6326.1026","name":"Microsoft Office 2016","length":2},"suffixes":"","type":"application/x-sharepoint"},"application/x-sharepoint-uc":{toString: function () {return "[object MimeType]";},"description":"","enabledPlugin":{"0":{},"1":{},"application/x-sharepoint":{},"application/x-sharepoint-uc":{},"item":"","namedItem":"","description":"The plugin allows you to have a better experience with Microsoft SharePoint","filename":"NPSPWRAP.DLL","version":"16.0.6326.1026","name":"Microsoft Office 2016","length":2},"suffixes":"","type":"application/x-sharepoint-uc"},"application/x-shockwave-flash":{toString: function () {return "[object MimeType]";},"description":"Adobe Flash movie","enabledPlugin":{"0":{},"1":{},"application/x-shockwave-flash":{},"application/futuresplash":{},"item":"","namedItem":"","description":"Shockwave Flash 20.0 r0","filename":"NPSWF32_20_0_0_306.dll","version":"20.0.0.306","name":"Shockwave Flash","length":2},"suffixes":"swf","type":"application/x-shockwave-flash"},"application/x-vnd-intel-webapi-ipt-4.0.68":{toString: function () {return "[object MimeType]";},"description":"npIntelWebAPIipt-3-5","enabledPlugin":{"0":{},"application/x-vnd-intel-webapi-ipt-4.0.68":{},"item":"","namedItem":"","description":"Intel web components for Intel® Identity Protection Technology","filename":"npIntelWebAPIIPT.dll","version":"4.0.68.0","name":"Intel® Identity Protection Technology","length":1},"suffixes":"","type":"application/x-vnd-intel-webapi-ipt-4.0.68"},"application/x-vnd-intel-webapi-updater":{toString: function () {return "[object MimeType]";},"description":"npIntelWebAPIupdater-2-0","enabledPlugin":{"0":{},"application/x-vnd-intel-webapi-updater":{},"item":"","namedItem":"","description":"Intel web components updater - Installs and updates the Intel web components","filename":"npIntelWebAPIUpdater.dll","version":"4.0.68.0","name":"Intel® Identity Protection Technology","length":1},"suffixes":"intel_webapi_updater-2-0","type":"application/x-vnd-intel-webapi-updater"},"item":{toString: function () { return "function item() {    [native code]}";}},"namedItem":{toString: function () { return "function namedItem() {    [native code]}";}},"length":7},"document":{"mozSetImageElement":{toString: function () { return "function mozSetImageElement() {    [native code]}";}},"mozCancelFullScreen":{toString: function () { return "function mozCancelFullScreen() {    [native code]}";}},"mozExitPointerLock":{toString: function () { return "function mozExitPointerLock() {    [native code]}";}},"mozFullScreenEnabled":false,"mozFullScreenElement":null,"mozFullScreen":false,"mozPointerLockElement":null,"mozHidden":false,"mozVisibilityState":"visible","onmozfullscreenchange":null,"onmozfullscreenerror":null,"onmozpointerlockchange":null,"onmozpointerlockerror":null,"document.documentElement":{"onmozfullscreenchange":null,"onmozfullscreenerror":null,"onmozpointerlockchange":null,"onmozpointerlockerror":null,"mozMatchesSelector":{toString: function () { return "function mozMatchesSelector() {    [native code]}";}},"mozRequestFullScreen":{toString: function () { return "function mozRequestFullScreen() {    [native code]}";}},"mozRequestPointerLock":{toString: function () { return "function mozRequestPointerLock() {    [native code]}";}},"clientWidth":19,"clientHeight":19}}}